{
  "hash": "ab4d2c1b",
  "browserHash": "86825f9d",
  "optimized": {
    "@vue/devtools-api": {
      "src": "../../../../node_modules/.pnpm/@vue+devtools-api@6.4.4/node_modules/@vue/devtools-api/lib/esm/index.js",
      "file": "@vue_devtools-api.js",
      "fileHash": "0c3d9e2d",
      "needsInterop": false
    },
    "@vue/shared": {
      "src": "../../../../node_modules/.pnpm/@vue+shared@3.2.41/node_modules/@vue/shared/dist/shared.esm-bundler.js",
      "file": "@vue_shared.js",
      "fileHash": "70df852c",
      "needsInterop": false
    },
    "@vuepress/shared": {
      "src": "../../../../node_modules/.pnpm/@vuepress+shared@2.0.0-beta.51/node_modules/@vuepress/shared/dist/index.js",
      "file": "@vuepress_shared.js",
      "fileHash": "0db0c41a",
      "needsInterop": false
    },
    "@vueuse/core": {
      "src": "../../../../node_modules/.pnpm/@vueuse+core@9.3.0_vue@3.2.37/node_modules/@vueuse/core/index.mjs",
      "file": "@vueuse_core.js",
      "fileHash": "377b0ec3",
      "needsInterop": false
    },
    "lodash-es": {
      "src": "../../../../node_modules/.pnpm/lodash-es@4.17.21/node_modules/lodash-es/lodash.js",
      "file": "lodash-es.js",
      "fileHash": "8eff7560",
      "needsInterop": false
    },
    "lodash-unified": {
      "src": "../../../../node_modules/.pnpm/lodash-unified@1.0.2_@types+lodash-es@4.17.6_lodash-es@4.17.21_lodash@4.17.21/node_modules/lodash-unified/import.js",
      "file": "lodash-unified.js",
      "fileHash": "26300ab0",
      "needsInterop": false
    },
    "vue": {
      "src": "../../../../node_modules/.pnpm/vue@3.2.37/node_modules/vue/dist/vue.runtime.esm-bundler.js",
      "file": "vue.js",
      "fileHash": "0337dd0c",
      "needsInterop": false
    },
    "vue-router": {
      "src": "../../../../node_modules/.pnpm/vue-router@4.1.5_vue@3.2.37/node_modules/vue-router/dist/vue-router.esm-bundler.js",
      "file": "vue-router.js",
      "fileHash": "981ed3a3",
      "needsInterop": false
    }
  },
  "chunks": {
    "chunk-6ZB4ZNPK": {
      "file": "chunk-6ZB4ZNPK.js"
    },
    "chunk-Q5NKSJD6": {
      "file": "chunk-Q5NKSJD6.js"
    },
    "chunk-62YVMR5A": {
      "file": "chunk-62YVMR5A.js"
    },
    "chunk-JEFOGESD": {
      "file": "chunk-JEFOGESD.js"
    }
  }
}